kios/__init__.py
kios/__main__.py
kios/cli.py
kios/config.py
kios/core.py
kios/data.py
kios/db.py
kios/exception.py
kios/factory.py
kios/operation.py
kios/parser.py
kios/protocol.py
kios/system.py
kios-0.1.dist-info/LICENSE
kios-0.1.dist-info/METADATA
kios-0.1.dist-info/WHEEL
kios-0.1.dist-info/entry_points.txt
kios-0.1.dist-info/top_level.txt
kios-0.1.dist-info/RECORD
