Metadata-Version: 2.1
Name: kios
Version: 0.1
Summary: Tool to collect and store TCP/UDP port usage data
Home-page: https://github.com/apleshakov/kios
Author: Andrey Pleshakov
Author-email: aplshkv@gmail.com
License: Apache-2.0
Platform: UNKNOWN
Classifier: Environment :: Console
Classifier: License :: OSI Approved :: Apache Software License
Classifier: Natural Language :: English
Classifier: Operating System :: Microsoft :: Windows
Classifier: Programming Language :: Python :: 3.8
Classifier: Topic :: Utilities
Requires-Python: >=3.8.1
Requires-Dist: sqlalchemy (>=1.3.12)
Requires-Dist: transitions (>=0.7.1)
